gxp_proxy/__init__.py
gxp_proxy/proxy.py
gcp_proxy-0.1.dist-info/METADATA
gcp_proxy-0.1.dist-info/WHEEL
gcp_proxy-0.1.dist-info/top_level.txt
gcp_proxy-0.1.dist-info/RECORD
